pycalendars/GoogleCalendar.py
pycalendars/ICloudCalendar.py
pycalendars/__init__.py
pycalendars-0.0.1.dist-info/LICENSE
pycalendars-0.0.1.dist-info/METADATA
pycalendars-0.0.1.dist-info/WHEEL
pycalendars-0.0.1.dist-info/top_level.txt
pycalendars-0.0.1.dist-info/RECORD
