Metadata-Version: 2.1
Name: pycalendars
Version: 0.0.1
Summary: A simple library to access your online calendars
Home-page: https://github.com/rmic/pycalendars
Author: Raphael Michel
Author-email: raph.mic@gmail.com
License: UNKNOWN
Platform: UNKNOWN
Classifier: Programming Language :: Python :: 3
Classifier: License :: OSI Approved :: MIT License
Classifier: Operating System :: OS Independent
Requires-Python: >=3.6
